annotator/__init__.py
annotator/annotation.py
annotator/atoi.py
annotator/auth.py
annotator/authz.py
annotator/document.py
annotator/elasticsearch.py
annotator/reindexer.py
annotator/store.py
annotator-0.14.2.dist-info/DESCRIPTION.rst
annotator-0.14.2.dist-info/METADATA
annotator-0.14.2.dist-info/metadata.json
annotator-0.14.2.dist-info/pbr.json
annotator-0.14.2.dist-info/RECORD
annotator-0.14.2.dist-info/top_level.txt
annotator-0.14.2.dist-info/WHEEL
