Metadata-Version: 2.0
Name: annotator
Version: 0.14.2
Summary: Database backend for Annotator (http://annotatorjs.org)
Home-page: http://annotatorjs.org/
Author: Rufus Pollock and Nick Stenning (Open Knowledge Foundation)
Author-email: annotator@okfn.org
License: MIT
Download-URL: https://github.com/openannotation/annotator-store
Keywords: annotation web javascript
Platform: UNKNOWN
Classifier: Development Status :: 4 - Beta
Classifier: Environment :: Console
Classifier: Intended Audience :: Developers
Classifier: License :: OSI Approved :: MIT License
Classifier: Operating System :: OS Independent
Classifier: Programming Language :: Python
Requires-Dist: elasticsearch (>=1.0,<2)
Requires-Dist: PyJWT (>=0.1.4)
Requires-Dist: iso8601 (>=0.1.4)
Requires-Dist: six
Provides-Extra: docs
Requires-Dist: Sphinx; extra == 'docs'
Provides-Extra: flask
Requires-Dist: Flask (>=0.9,<2); extra == 'flask'
Provides-Extra: testing
Requires-Dist: Flask (>=0.9,<2); extra == 'testing'
Requires-Dist: mock; extra == 'testing'
Requires-Dist: nose; extra == 'testing'
Requires-Dist: coverage; extra == 'testing'
